mlpdf/__init__.py
mlpdf/data/All_ML_programs.pdf
tezcontext-0.1.0.dist-info/METADATA
tezcontext-0.1.0.dist-info/WHEEL
tezcontext-0.1.0.dist-info/top_level.txt
tezcontext-0.1.0.dist-info/RECORD
