Metadata-Version: 2.1
Name: tezcontext
Version: 0.1.0
Summary: Access to All ML programs PDF
Author: Tez
